is_relevant/__init__.py
is_relevant/convert_request.py
eias_check_relevant-1.0.2.dist-info/LICENSE
eias_check_relevant-1.0.2.dist-info/METADATA
eias_check_relevant-1.0.2.dist-info/WHEEL
eias_check_relevant-1.0.2.dist-info/top_level.txt
eias_check_relevant-1.0.2.dist-info/RECORD
