Metadata-Version: 2.1
Name: eias-check-relevant
Version: 1.0.2
Summary: A small package that checks date relevant for EIAS system
Home-page: https://github.com/J4CKVVH173/eias_check_relevant
Author: J4CK_VVH173
Author-email: i78901234567890@gmail.com
Classifier: Programming Language :: Python :: 3
Classifier: License :: OSI Approved :: MIT License
Classifier: Operating System :: OS Independent
Requires-Python: >=3.6
License-File: LICENSE
